Workbook

Sheet Requirements
A1: Remote control – Needs analysis (FP4)
A2: FP4 : the remote control must be able to pilot the robot remotely
A4: 1. Criteria of function FP4 (from the specifications)
A5: Criterion | B5: Level | C5: Unit | D5: Source
A6: Minimum radio range (indoor) | B6: 30 | C6: m | D6: Specifications : function table (FP4)
A7: Minimum radio range (outdoor) | B7: 150 | C7: m | D7: Specifications : function table (FP4)
A8: Maximum response time of the control | B8: 50 | C8: ms | D8: Specifications : function table (FP4)
A10: 2. Input/output needs of the remote control (based on the electronic diagram)
A11: Control element | B11: No. of elements | C11: Analog. channels / element | D11: Digital inputs / element | E11: Digital outputs / element | F11: I2C pins / element | G11: Total analog | H11: Total digital inputs | I11: Total digital outputs | J11: Total I2C pins | K11: Role on the robot (to be completed)
A12: 2-axis joystick (KY-023) | B12: 2 | C12: 2 | D12: 1 | E12: 0 | F12: 0 | G12: =$B12*C12 -> 4 | H12: =$B12*D12 -> 2 | I12: =$B12*E12 -> 0 | J12: =$B12*F12 -> 0 | K12: Joystick 1 : forward/backward (Y axis) + turn right/left (X axis) ; Joystick 2 : tilt right/left (X axis) + lower/raise (Y axis)
A13: Slide potentiometer | B13: 3 | C13: 1 | D13: 0 | E13: 0 | F13: 0 | G13: =$B13*C13 -> 3 | H13: =$B13*D13 -> 0 | I13: =$B13*E13 -> 0 | J13: =$B13*F13 -> 0 | K13: Adjustment of the robot's 3 PID controller gains (P, I, D)
A14: Rotary potentiometer | B14: 1 | C14: 1 | D14: 0 | E14: 0 | F14: 0 | G14: =$B14*C14 -> 1 | H14: =$B14*D14 -> 0 | I14: =$B14*E14 -> 0 | J14: =$B14*F14 -> 0 | K14: Adjustment of the maximum travel speed
A15: Push button | B15: 5 | C15: 0 | D15: 1 | E15: 0 | F15: 0 | G15: =$B15*C15 -> 0 | H15: =$B15*D15 -> 5 | I15: =$B15*E15 -> 0 | J15: =$B15*F15 -> 0 | K15: 1 button = jump ; 4 buttons = macros / screen navigation
A16: Signal LED | B16: 1 | C16: 0 | D16: 0 | E16: 1 | F16: 0 | G16: =$B16*C16 -> 0 | H16: =$B16*D16 -> 0 | I16: =$B16*E16 -> 1 | J16: =$B16*F16 -> 0 | K16: Power-on status
A17: OLED screen (I2C) | B17: 1 | C17: 0 | D17: 0 | E17: 0 | F17: 2 | G17: =$B17*C17 -> 0 | H17: =$B17*D17 -> 0 | I17: =$B17*E17 -> 0 | J17: =$B17*F17 -> 2 | K17: Menu navigation, communication parameter settings, robot information display (speed, battery,…)
A18: On / off switch | B18: 1 | C18: 0 | D18: 0 | E18: 0 | F18: 0 | G18: =$B18*C18 -> 0 | H18: =$B18*D18 -> 0 | I18: =$B18*E18 -> 0 | J18: =$B18*F18 -> 0 | K18: In series with the power supply
A19: Digital voltmeter | B19: 1 | C19: 0 | D19: 0 | E19: 0 | F19: 0 | G19: =$B19*C19 -> 0 | H19: =$B19*D19 -> 0 | I19: =$B19*E19 -> 0 | J19: =$B19*F19 -> 0 | K19: Connected to the battery
A20: TOTAL | G20: =SUM(G12:G19) -> 8 | H20: =SUM(H12:H19) -> 7 | I20: =SUM(I12:I19) -> 1 | J20: =SUM(J12:J19) -> 2
A22: 3. Summary : what the remote control must provide (microcontroller selection criteria)
A23: Indicator | B23: Value | C23: Comment
A24: Analog channels to acquire | B24: =G20 -> 8 | C24: 2 joysticks × 2 axes + 3 sliders + 1 rotary
A25: Digital inputs (buttons) | B25: =H20 -> 7 | C25: 5 buttons + 2 buttons integrated into the joysticks
A26: Digital outputs | B26: =I20 -> 1 | C26: Signal LED
A27: I2C pins (SDA + SCL) | B27: =J20 -> 2 | C27: OLED screen
A28: Total GPIO pins required | B28: =SUM(B24:B27) -> 18 | C28: The microcontroller must provide at least this number of usable GPIOs
A29: Values to be transmitted per radio frame | B29: =B24+B25 -> 15 | C29: Analog channels + button states (to be sent to the robot)
A30: Minimum transmission frequency (Hz) | B30: =1/(50*10^(-3)) -> 20 | C30: At least 1 complete transmission per maximum response time
A31: Selected transmission frequency (Hz) | B31: 50 | C31: Assumption : 50 Hz (×2.5 margin over the minimum)
A32: Transmission period (ms) | B32: =1000/B31 -> 20 | C32: Maximum delay between two frames
A33: Estimated radio latency + robot processing (ms) | B33: 10 | C33: Assumption : ESP-NOW ≈ a few ms + robot-side reading
A34: Estimated response time (ms) | B34: =B32+B33 -> 30 | C34: Transmission period + latency

Sheet Component Selection
A1: Remote control - Component selection
A2: Justification of each component with respect to function FP4 (piloting the robot remotely)
A4: No. | B4: Function performed | C4: Component selected | D4: Reference / model | E4: Main characteristics | F4: Justification of choice | G4: Alternatives considered | H4: Alternative drawbacks | I4: Qty | J4: Unit price (€) | K4: Total price (€)
A5: 1 | B5: Command processing (acquisition, computation, screen interface) | C5: Microcontroller | D5: ESP32-S3-DevKitC-1-N16R8 | E5: Dual-core Xtensa LX7 240 MHz · 16 MB Flash + 8 MB PSRAM, 3.3 V logic supply, many GPIOs including 10 channels usable on ADC1 | F5: Enough GPIOs and ADC1 channels for the 18 pins required (see sheet « Requirements »). | G5: Arduino Nano | H5: No built-in radio, little memory, fewer ADC inputs | I5: 1 | J5: 8 | K5: =IF(ISNUMBER(J5),I5*J5,"") -> 8
G6: ESP32-S3 version N8R2/N8R8 | H6: Less Flash/PSRAM, lower memory margin
G7: STM32 | H7: More processing power but radio and Wi-Fi must be added as an external module
A8: 2 | B8: Radio link control → robot | C8: Communication protocol | D8: ESP-NOW (2.4 GHz Wi-Fi, native on the ESP32-S3) | E8: Typical latency of a few ms, potential range with this board : > 200 m outdoor with no obstacles, > 100 m outdoor with obstacles, > 20 m indoor | F8: Latency compatible with the required response time (< 50 ms). Built into the ESP32-S3 : no external radio module to wire. | G8: Detailed comparison against other solutions in the sheet « Radio Comparison ».
A9: 3 | B9: Proportional control of movement and orientation | C9: 2-axis joystick | D9: Module KY-023 | E9: 2 10 kΩ potentiometers (X and Y axes) + built-in push button, 3.3-5 V supply | F9: Proportional analog signal. Joystick 1 = forward/backward (Y axis) and turn right/left (X axis) ; Joystick 2 = tilt right/left (X axis) and lower/raise (Y axis). | G9: Directional buttons | H9: On/off only, no gradual control | I9: 2 | J9: 4 | K9: =IF(ISNUMBER(J9),I9*J9,"") -> 8
A10: 4 | B10: Proportional adjustment of the controller gains | C10: Slide potentiometer | D10: Linear slide potentiometer | E10: 10 kΩ linear resistive track, 3 pins | F10: PID position readable at a glance, gradual and precise adjustment, 1 analog channel each. | G10: Rotary potentiometer | H10: Less readable | I10: 3 | J10: 1.6 | K10: =IF(ISNUMBER(J10),I10*J10,"") -> 4.8
G11: Incremental encoder | H11: More connectors used per value to change
A12: 5 | B12: Speed adjustment | C12: Rotary potentiometer | D12: VRB-101M10 | E12: 10 kΩ, 3 pins | F12: Gradual and compact adjustment, easy to read for speed | G12: Slide potentiometer | H12: Bulkier and less readable | I12: 1 | J12: 0.5 | K12: =IF(ISNUMBER(J12),I12*J12,"") -> 0.5
G13: Rotary encoder | H13: No physical stop, more connectors used
A14: 6 | B14: On/off commands and macros | C14: Push button | D14: BP-GT1-ON | E14: Momentary open contact, read with the ESP32's internal pull-up/pull-down | F14: Simple, reliable, low-cost, 1 digital input each, with no additional external component. | G14: Toggle switch | H14: Does not natively return to its initial position | I14: 5 | J14: 0.3 | K14: =IF(ISNUMBER(J14),I14*J14,"") -> 1.5
G15: Touchscreen | H15: Less ergonomic for handling and teleguidance
A16: 7 | B16: Feedback and navigation for the operator | C16: OLED screen 0.96" | D16: Module SSD1306 128*64, I2C | E16: 0.96", 128×64 px, 4-wire I2C bus (2 GPIO pins : SDA/SCL) | F16: No. of pins : only 2 GPIO pins (I2C). Size : 0.96" compact, fits easily into the remote control's housing while remaining readable. Ease of use : well-documented libraries | G16: LCD display 16×2 I2C | H16: Same number of pins but lower resolution and readability | I16: 1 | J16: 4 | K16: =IF(ISNUMBER(J16),I16*J16,"") -> 4
G17: TFT SPI screen | H17: Larger and in color but ≈ 5 pins, more expensive, higher current draw
G18: OLED 1.3" | H18: More readable but slightly more expensive and bulkier on the remote control
A19: 8 | B19: Status signaling | C19: LED | D19: LED 5 mm | F19: Immediate power-on indication, negligible cost. | G19: RGB LED | H19: Mandatory pin on the ESP32 | I19: 1 | J19: 0.1 | K19: =IF(ISNUMBER(J19),I19*J19,"") -> 0.1
G20: Information displayed only on the OLED | H20: Harder to diagnose the source of a fault if the screen is not working
A21: 9 | B21: Autonomous power supply | C21: LiPo battery | D21: 2S 500 mAh LiPo battery | E21: 2S (7.4 V nominal), 500 mAh, JST connector | F21: Battery life : 500 mAh capacity sufficient for one session of use (battery life estimated in the sheet « Energy Balance »). Size / weight : compact and lightweight, suited to a hand-held remote control. | G21: Higher-capacity 2S LiPo | H21: Increased battery life but heavier and bulkier | I21: 1 | J21: 8 | K21: =IF(ISNUMBER(J21),I21*J21,"") -> 8
G22: LiPo 1S | H22: Lighter but voltage too low, would require a boost converter
G23: rechargeable AA batteries | H23: Heavier, voltage drops during discharge
A24: 10 | B24: Supply voltage adaptation | C24: DC-DC step-down converter | D24: Adjustable LM2596 module | E24: Input 4-40 V, adjustable output 1.25-35 V, 3 A max, efficiency ≈ 80-90 % | F24: Converts the variable LiPo voltage into a stable 5 V for the ESP. Largely oversized for the power consumption (see sheet « Energy Balance »). | G24: LM7805 | H24: Lower efficiency, heat losses | I24: 1 | J24: 5 | K24: =IF(ISNUMBER(J24),I24*J24,"") -> 5
A25: 11 | B25: Battery monitoring | C25: Digital voltmeter | D25: 3-digit DC voltmeter | E25: Typical range ≈ 3-10 V, 3-digit LED display, powered by the measured voltage | F25: Immediate reading of the charge state, without using an analog input connected to the microcontroller. | G25: Voltage divider + ESP32 ADC, displayed on the OLED | H25: Harder to diagnose the source of a fault if the screen is not working | I25: 1 | J25: 3 | K25: =IF(ISNUMBER(J25),I25*J25,"") -> 3
A26: 12 | B26: On / off | C26: Toggle switch | D26: Lever switch | E26: Rating higher than the circuit current (≈ 0.2 A) | F26: Real power cut-off, no GPIO pin required, simple to operate. | G26: Unplug the battery | H26: Less ergonomic | I26: 1 | J26: 1 | K26: =IF(ISNUMBER(J26),I26*J26,"") -> 1
A27: TOTAL | I27: =SUM(I5:I26) -> 18 | K27: =SUM(K5:K26) -> 43.9

Sheet Radio Comparison
A1: Remote control – Comparison of radio / microcontroller solutions
A2: Choice of the wireless link solution (FP4 elimination criteria, then weighted scoring)
A4: A. Solutions considered with typical orders of magnitude and compliance with FP4
A5: Criterion | B5: Unit | C5: ESP32-S3 + ESP-NOW | D5: Arduino Nano + nRF24L01 (PA/LNA) | E5: Arduino + LoRa (SX1278) | F5: Bluetooth module HC-05
A6: Frequency band | C6: 2.4 GHz | D6: 2.4 GHz | E6: 433 / 868 MHz | F6: 2.4 GHz
A7: Typical outdoor range (direct line of sight) | B7: m | C7: 200 | D7: 800 | E7: 2000 | F7: 10
A8: Typical link latency | B8: ms | C8: 5 | D8: 3 | E8: 200 | F8: 30
A9: Meets the FP4 outdoor range ? | C9: =IF(C7>=Requirements!$B$7,"YES","NO") -> YES | D9: =IF(D7>=Requirements!$B$7,"YES","NO") -> YES | E9: =IF(E7>=Requirements!$B$7,"YES","NO") -> YES | F9: =IF(F7>=Requirements!$B$7,"YES","NO") -> NO
A10: Meets the FP4 response time ? | C10: =IF(C8<Requirements!$B$8,"YES","NO") -> YES | D10: =IF(D8<Requirements!$B$8,"YES","NO") -> YES | E10: =IF(E8<Requirements!$B$8,"YES","NO") -> NO | F10: =IF(F8<Requirements!$B$8,"YES","NO") -> YES
A11: Compliant with function FP4 ? | C11: =IF(AND(C9="YES",C10="YES"),"YES","NO") -> YES | D11: =IF(AND(D9="YES",D10="YES"),"YES","NO") -> YES | E11: =IF(AND(E9="YES",E10="YES"),"YES","NO") -> NO | F11: =IF(AND(F9="YES",F10="YES"),"YES","NO") -> NO
A13: B. Weighted scoring (0 = very unfavorable … 5 = very favorable) – indicative scores to be adjusted
A14: Criterion | B14: Weight | C14: ESP32-S3 + ESP-NOW | D14: Arduino Nano + nRF24L01 (PA/LNA) | E14: Arduino + LoRa (SX1278) | F14: Bluetooth module HC-05
A15: Outdoor range | B15: 0.25 | C15: 4 | D15: 5 | E15: 5 | F15: 1
A16: Latency / responsiveness | B16: 0.2 | C16: 5 | D16: 5 | E16: 1 | F16: 3
A17: Number of I/Os and analog channels | B17: 0.15 | C17: 5 | D17: 3 | E17: 3 | F17: 3
A18: Ease of implementation (wiring, code) | B18: 0.15 | C18: 4 | D18: 3 | E18: 2 | F18: 4
A19: Cost | B19: 0.1 | C19: 5 | D19: 4 | E19: 2 | F19: 4
A20: Power consumption | B20: 0.1 | C20: 3 | D20: 4 | E20: 4 | F20: 3
A21: Integration / size | B21: 0.05 | C21: 5 | D21: 3 | E21: 2 | F21: 3
A22: Total weight (must equal 100 %) | B22: =SUM(B15:B21) -> 1
A23: Score out of 20 | C23: =SUMPRODUCT($B$15:$B$21,C15:C21)*4 -> 17.6 | D23: =SUMPRODUCT($B$15:$B$21,D15:D21)*4 -> 16.4 | E23: =SUMPRODUCT($B$15:$B$21,E15:E21)*4 -> 11.6 | F23: =SUMPRODUCT($B$15:$B$21,F15:F21)*4 -> 11
A24: Score retained (0 if not compliant with FP4) | C24: =IF(C11="YES",C23,0) -> 17.6 | D24: =IF(D11="YES",D23,0) -> 16.4 | E24: =IF(E11="YES",E23,0) -> 0 | F24: =IF(F11="YES",F23,0) -> 0
A25: Rank | C25: =RANK(C24,$C$24:$F$24) -> 1 | D25: =RANK(D24,$C$24:$F$24) -> 2 | E25: =RANK(E24,$C$24:$F$24) -> 3 | F25: =RANK(F24,$C$24:$F$24) -> 3
A26: Decision | C26: =IF(C25=1,"SELECTED",IF(C11="NO","Eliminated (FP4)","Not selected")) -> SELECTED | D26: =IF(D25=1,"SELECTED",IF(D11="NO","Eliminated (FP4)","Not selected")) -> Not selected | E26: =IF(E25=1,"SELECTED",IF(E11="NO","Eliminated (FP4)","Not selected")) -> Eliminated (FP4) | F26: =IF(F25=1,"SELECTED",IF(F11="NO","Eliminated (FP4)","Not selected")) -> Eliminated (FP4)

Sheet Energy Balance
A1: Remote control – Energy balance and battery life
A2: Justifies the choice of the LiPo battery and the LM2596 converter
A4: 1. Power supply parameters
A5: Parameter | B5: Value | C5: Comment
A6: Nominal battery voltage (V) | B6: 7.4 | C6: Battery selected : 2S LiPo (7.4 V nominal)
A7: Battery capacity (mAh) | B7: 500 | C7: Battery selected : 2S 500 mAh LiPo
A8: Usable capacity fraction | B8: 0.8 | C8: Assumption : 80 % (to avoid fully discharging the battery)
A9: LM2596 output voltage (V) | B9: 5 | C9: Set to 5 V to power the ESP32 board
A10: Converter efficiency | B10: 0.8 | C10: Assumption : 85 % (typical 80–90 % for an LM2596)
A12: 2. Element power consumption
A13: Element | B13: Qty | C13: Unit current (mA) | D13: Powered by | E13: Total current (mA) | F13: Assumption / source
A14: ESP32-S3 (ESP-NOW transmission) | B14: 1 | C14: 120 | D14: 5 V rail | E14: =B14*C14 -> 120 | F14: Average during Wi-Fi transmission -> higher peaks
A15: OLED screen 0.96" SSD1306 | B15: 1 | C15: 20 | D15: 5 V rail | E15: =B15*C15 -> 20 | F15: Screen on and changing image at 2Hz
A16: Joystick KY-023 | B16: 2 | C16: 1 | D16: 5 V rail | E16: =B16*C16 -> 2 | F16: 2 10 kΩ potentiometers at 3.3 V ≈ 0.7 mA
A17: Slide potentiometer | B17: 3 | C17: 0.5 | D17: 5 V rail | E17: =B17*C17 -> 1.5 | F17: 10 kΩ at 3.3 V ≈ 0.33 mA
A18: Rotary potentiometer | B18: 1 | C18: 0.5 | D18: 5 V rail | E18: =B18*C18 -> 0.5 | F18: 10 kΩ at 3.3 V ≈ 0.33 mA
A19: Signal LED | B19: 1 | C19: 10 | D19: 5 V rail | E19: =B19*C19 -> 10 | F19: LED permanently on
A20: Digital voltmeter | B20: 1 | C20: 10 | D20: 5V rail | E20: =B20*C20 -> 10 | F20: Connected to the output of the 7.4V->5V converter
A23: 3. Results
A24: Indicator | B24: Value | C24: Comment
A25: Total current on the 5 V rail (mA) | B25: =SUM(E14:E20) -> 164 | C25: Sum of the elements powered by the converter
A26: Power on the 5 V rail (mW) | B26: =B25*B9 -> 820 | C26: P = U * I
A27: Current drawn from the battery (mA) | B27: =B26/(B6*B10) -> 138.51351 | C27: Rail power referred back to the battery (efficiency included)
A28: Estimated battery life (h) | B28: =B7*B8/B27 -> 2.8878049 | C28: Usable capacity / current drawn
A29: Max. LM2596 current (mA) | B29: 3000 | C29: Manufacturer value : 3 A
A30: Voltage margin Vbattery − Voutput (V) | B30: =B6-B9 -> 2.4 | C30: The LM2596 requires a minimum input difference of about 2 V
A31: Sufficient voltage margin ? | B31: =IF(B30>=2,"YES","NO") -> YES | C31: To be checked when the battery is discharged
